notefight/__init__.py
notefight/tianchi/__init__.py
notefight/tianchi/t531800/__init__.py
notefight/tianchi/t531800/ai_flow_master.py
notefight/tianchi/t531800/kafka-source.py
notefight/tianchi/t531800/step1.py
notefight-0.0.3.dist-info/METADATA
notefight-0.0.3.dist-info/WHEEL
notefight-0.0.3.dist-info/top_level.txt
notefight-0.0.3.dist-info/RECORD
