Metadata-Version: 2.1
Name: notefight
Version: 0.0.3
Summary: notefight
Home-page: https://github.com/1007530194
Author: euler
Author-email: 1007530194@qq.com
License: UNKNOWN
Platform: UNKNOWN
Requires-Dist: notetool
Requires-Dist: notedata
Requires-Dist: notedrive
